{
    "beam_diameter": "1.0", 
    "cleanup_duration": 30.0, 
    "commit": "7da5ca8668a89578598ec8ff72a817e088dab9cd", 
    "extract_device": "Fusions CO2", 
    "extract_duration": 30.0, 
    "extract_units": "watts", 
    "extract_value": 0.2, 
    "pattern": "", 
    "positions": [
        {
            "is_degas": false, 
            "position": "134", 
            "x": null, 
            "y": null, 
            "z": null
        }
    ], 
    "ramp_duration": 0.0, 
    "ramp_rate": 0.0, 
    "request": "Tm8gUmVzcG9uc2U=", 
    "response": "Tm8gUmVzcG9uc2U=", 
    "sblob": "", 
    "tray": "", 
    "weight": 0.0
}