{
    "AX": {
        "error": 0.007195938823114368, 
        "filter_outliers_dict": {
            "filter_outliers": true, 
            "iterations": 1, 
            "std_devs": 2
        }, 
        "fit": "average", 
        "value": 0.038303245935524546
    }, 
    "CDD": {
        "error": 3.5256442675702835e-06, 
        "filter_outliers_dict": {
            "filter_outliers": true, 
            "iterations": 1, 
            "std_devs": 10
        }, 
        "fit": "average", 
        "value": 5.028813127216967e-06
    }, 
    "H1": {
        "error": 0.005529698161339519, 
        "filter_outliers_dict": {
            "filter_outliers": true, 
            "iterations": 1, 
            "std_devs": 2
        }, 
        "fit": "average", 
        "value": -0.04652192040564138
    }, 
    "H2": {
        "error": 0.006075572883588747, 
        "filter_outliers_dict": {
            "filter_outliers": true, 
            "iterations": 1, 
            "std_devs": 2
        }, 
        "fit": "average", 
        "value": 0.07434350239931559
    }, 
    "L1": {
        "error": 0.0023742990409055084, 
        "filter_outliers_dict": {
            "filter_outliers": true, 
            "iterations": 1, 
            "std_devs": 2
        }, 
        "fit": "average", 
        "value": -0.008590498635058216
    }, 
    "L2": {
        "error": 0.005397551436502986, 
        "filter_outliers_dict": {
            "filter_outliers": true, 
            "iterations": 1, 
            "std_devs": 2
        }, 
        "fit": "average", 
        "value": 0.12896375471833157
    }
}